[{"t": -510, "type": "other", "side": "USN", "s": "Jonction TF-16/TF-17 à Point Luck (~32°N 173°W, 045°/325 nm de Midway); Fletcher (Yorktown) prend le commandement tactique; TF-16 prend station à 10 nm au sud", "u": 30}, {"t": 1, "type": "other", "side": "IJN", "s": "Plan MI: route d'approche du groupe de transport vers Midway (débarquement prévu le 6); cap ENE ~10 nds", "u": 0}, {"t": 255, "type": "launch_start", "side": "USN", "s": "Recherche quotidienne du 3 juin: les PBY partent en éventail (dont la ligne OSO de Reid, VP-44)", "u": 15}, {"t": 540, "type": "sighting", "side": "USN", "s": "PBY de VP-44 (Ens. Reid) repère le groupe de transport à ~450 nm OSO de Midway (relèvement ~253°); rapporté à tort comme \"Main Body\"", "u": 15}, {"t": 750, "type": "launch_start", "side": "USN", "s": "Midway lance 9 B-17 (Sweeney) contre le groupe de transport", "u": 15}, {"t": 984, "type": "attack", "side": "USN", "s": "B-17 attaquent les transports à haute altitude — aucun coup au but", "u": 15}, {"t": 1190, "type": "course_change", "side": "USN", "s": "Fletcher vire au 210° à 13,5 nœuds pour positionner les TF face aux vents du sud, en vue du lancement de l'aube du 4", "u": 20}, {"t": 1275, "type": "launch_start", "side": "USN", "s": "4 PBY-5A équipés radar décollent de Midway pour l'attaque de nuit à la torpille contre le convoi d'invasion", "u": 15}, {"t": 1543, "type": "hit", "side": "USN", "s": "Attaque de nuit de 4 PBY à la torpille; Akebono Maru touché (seul succès aérien torpille US de la bataille)", "u": 10}, {"t": 1695, "type": "launch_start", "side": "USN", "s": "Recherche du matin: ~22 PBY décollent de Midway (Sand + Eastern Island) en éventail jusqu'à ~700 nm — c'est elle qui donnera les contacts d'Ady (CV, 05:34) et de Chase (raid entrant, 05:45)", "u": 15}, {"t": 1710, "type": "launch_start", "side": "IJN", "s": "Kidō Butai lance la frappe sur Midway: 108 appareils (Tomonaga)", "u": 5}, {"t": 1710, "type": "launch_start", "side": "IJN", "s": "Lancement du plan de recherche (7 appareils, une seule phase); catapulte du Tone en panne", "u": 10}, {"t": 1725, "type": "launch_end", "side": "IJN", "s": "Fin du lancement de la frappe Tomonaga (108 appareils des 4 CV)", "u": 5}, {"t": 1740, "type": "launch_end", "side": "IJN", "s": "Hydravion n°4 du Tone (Amari) lancé avec ~30 min de retard — il couvrira la ligne où se trouvent les TF US", "u": 10}, {"t": 1774, "type": "sighting", "side": "USN", "s": "PBY 4V58 (Ady, VP-23) : \"enemy carriers\" — premier contact sur la Kidō Butai", "u": 3}, {"t": 1785, "type": "report", "side": "USN", "s": "PBY (Lt. W. Chase) en clair : \"many planes heading Midway, bearing 320, distance 150\" — l'alerte du raid entrant qui précipite le décollage général de Midway", "u": 3}, {"t": 1793, "type": "sighting", "side": "USN", "s": "Radar de Midway détecte le raid entrant (\"many planes, 89 miles\"); décollage général de tout ce qui vole", "u": 5}, {"t": 1803, "type": "report", "side": "USN", "s": "PBY 4V58 (Ady) : \"two carriers and battleships bearing 320, distance 180, course 135, speed 25\" — amplification du contact de 0534; position erronée de ~30-40 nm; ne signale que 2 CV sur 4", "u": 3}, {"t": 1807, "type": "decision", "side": "USN", "s": "Fletcher à Spruance : \"proceed southwesterly and attack enemy carriers when definitely located\" — TF-16 part en avant, TF-17 récupère sa recherche", "u": 3}, {"t": 1815, "type": "course_change", "side": "USN", "s": "Les 15 B-17 de Sweeney, en route vers le convoi de transport, sont déroutés vers les porte-avions japonais signalés par les PBY", "u": 20}, {"t": 1816, "type": "attack", "side": "USN", "s": "VMF-221 (Parks) intercepte la frappe Tomonaga: 25 chasseurs vs escorte de 36 Zeros — 13 F2A/F4F perdus, 7 endommagés", "u": 5}, {"t": 1830, "type": "attack", "side": "IJN", "s": "La frappe Tomonaga bombarde Midway (06:30-06:43): dégâts importants aux installations, pistes restent utilisables", "u": 5}, {"t": 1860, "type": "report", "side": "IJN", "s": "Tomonaga : \"il est nécessaire de procéder à une deuxième attaque\" (Kawa·Kawa·Kawa 109)", "u": 3}, {"t": 1866, "type": "launch_start", "side": "USN", "s": "TF-16 commence à lancer à ~155 nm de la position estimée de la KB (limite TBD); lancement long (~1h), escadrilles séparées en route", "u": 4}, {"t": 1870, "type": "attack", "side": "USN", "s": "6 TBF (Fieberling) + 4 B-26 (Collins) attaquent la KB sans escorte: aucun coup, 5 TBF et 2 B-26 perdus; un B-26 frôle la passerelle de l'Akagi", "u": 5}, {"t": 1875, "type": "decision", "side": "IJN", "s": "Nagumo ordonne le réarmement des B5N (torpilles -> bombes) pour 2e frappe sur Midway", "u": 5}, {"t": 1888, "type": "sighting", "side": "IJN", "s": "Hydravion n°4 du Tone signale 10 navires ennemis", "u": 5}, {"t": 1905, "type": "decision", "side": "IJN", "s": "Nagumo suspend le réarmement (ordre \"préparez-vous à attaquer les unités de flotte; laissez les torpilles aux appareils non encore réarmés\") et demande au Tone n°4 de préciser la composition ennemie", "u": 5}, {"t": 1915, "type": "attack", "side": "USN", "s": "16 SBD-2 VMSB-241 (Henderson) attaquent le Hiryū en glide-bombing: aucun coup, 8 perdus dont Henderson", "u": 5}, {"t": 1930, "type": "attack", "side": "USN", "s": "B-17 (Sweeney) bombardent les CV depuis ~6000 m: aucun coup", "u": 10}, {"t": 1940, "type": "attack", "side": "USN", "s": "11 SB2U (Norris) attaquent le Haruna: aucun coup", "u": 10}, {"t": 1940, "type": "report", "side": "IJN", "s": "Tone n°4 : \"l'ennemi est accompagné de ce qui semble être un porte-avions\" — le pivot informationnel de la bataille", "u": 5}, {"t": 1950, "type": "report", "side": "IJN", "s": "Yamaguchi (signal au Nagumo) : \"considère souhaitable de lancer la force d'attaque immédiatement\" — avec les D3A disponibles, sans escorte complète", "u": 10}, {"t": 1957, "type": "recovery_start", "side": "IJN", "s": "La KB commence à récupérer la frappe Tomonaga + la CAP (ponts monopolisés ~35 min)", "u": 5}, {"t": 1958, "type": "launch_start", "side": "USN", "s": "Yorktown lance: 17 VB-3, 12 VT-3, 6 VF-3 (Fletcher garde VS-5 en réserve) — fin ~09:06", "u": 5}, {"t": 1975, "type": "decision", "side": "IJN", "s": "Nagumo refuse la frappe immédiate: récupérer d'abord, puis frapper en force constituée vers 10:30 (\"fenêtre des 65 minutes\")", "u": 10}, {"t": 1990, "type": "recovery_end", "side": "IJN", "s": "Récupération terminée; réarmement/ravitaillement généralisé en hangar", "u": 10}, {"t": 1997, "type": "course_change", "side": "IJN", "s": "La KB vire au 070 (ENE) vers les porte-avions US — la frappe du Hornet (cap 265→240?) la manque en partie", "u": 5}, {"t": 2000, "type": "attack", "side": "USN", "s": "VT-8 (Waldron, 15 TBD seuls, sans escorte) attaque: tous abattus (~09:36), 1 survivant (Ens. Gay); aucun coup", "u": 5}, {"t": 2018, "type": "attack", "side": "USN", "s": "VT-6 (Lindsey, 14 TBD) attaque par les deux bords: 10 perdus, aucun coup; la CAP reste tirée à basse altitude", "u": 5}, {"t": 2035, "type": "decision", "side": "USN", "s": "McClusky, à sec de réserve, prolonge la recherche puis vire N-O; repère le sillage de l'Arashi (qui regagne la KB après avoir grenadé le Nautilus) et le suit", "u": 10}, {"t": 2042, "type": "sighting", "side": "USN", "s": "McClusky (CEAG, groupe Enterprise) repère la KB à ~35 nm au NE en suivant le sillage de l'Arashi — déclenche l'attaque en piqué", "u": 3}, {"t": 2055, "type": "attack", "side": "USN", "s": "VT-3 (Massey, 12 TBD) + VF-3 (Thach, 6 F4F) attaquent: 10 TBD perdus, aucun coup; Thach Weave employé pour la première fois; la CAP entière est au ras de l'eau", "u": 5}, {"t": 2060, "type": "spot", "side": "IJN", "s": "État réel des ponts (contra Fuchida): frappes encore en hangar, ponts occupés par la CAP; lancement prévu ~10:30-11:00", "u": 10}, {"t": 2062, "type": "hit", "side": "USN", "s": "VB-6/VS-6 frappent Kaga et Akagi; VB-3 frappe Sōryū (10:22–10:26)", "u": 2}, {"t": 2062, "type": "hit", "side": "USN", "s": "VS-6 + VB-6 (McClusky) plongent: Kaga touché 4-5 bombes (10:22-10:26) — hangars pleins de munitions: incendies incontrôlables", "u": 2}, {"t": 2065, "type": "hit", "side": "USN", "s": "VB-3 (Leslie): 3 coups sur le Sōryū — en flammes, stoppé à 10:40", "u": 2}, {"t": 2066, "type": "hit", "side": "USN", "s": "Section Best (3 SBD VB-6): 1 coup fatal sur l'Akagi (ascenseur central, hangar) + 1 near-miss arrière qui bloque le gouvernail? — incendies", "u": 2}, {"t": 2071, "type": "course_change", "side": "IJN", "s": "Le reliquat de la KB (Hiryū + escorte, Abe puis Yamaguchi) maintient le cap N-NE: continuer le combat et garder la portée de frappe", "u": 15}, {"t": 2085, "type": "recovery_start", "side": "USN", "s": "TF-16 interrompt sa progression SO: récupérations successives des raids du matin (SBD, chasse, rescapés VT, puis avions du Yorktown) face au vent d'E-SE — dérive nette vers le NE jusqu'à ~15:00", "u": 15}, {"t": 2086, "type": "other", "side": "IJN", "s": "Nagumo évacue l'Akagi et transfère sa marque sur le Nagara; Abe (CruDiv 8) commande l'intérim", "u": 10}, {"t": 2094, "type": "launch_start", "side": "IJN", "s": "Hiryū lance sa 1re frappe: 18 D3A + 6 A6M (Kobayashi), guidés en suivant les avions US au retour", "u": 5}, {"t": 2152, "type": "sighting", "side": "USN", "s": "Radar du Yorktown détecte le raid à ~32 nm; CAP renforcée, ravitaillement coupé, SBD éloignés du navire", "u": 5}, {"t": 2165, "type": "attack", "side": "IJN", "s": "Attaque Kobayashi (7 D3A passent la CAP): 3 bombes touchent le Yorktown (12:11-12:16); chaudières stoppées; Kobayashi tué", "u": 8}, {"t": 2251, "type": "launch_start", "side": "IJN", "s": "Hiryū lance sa 2e frappe: 10 B5N + 6 A6M (Tomonaga, réservoir gauche non réparé — aller simple assumé)", "u": 5}, {"t": 2260, "type": "other", "side": "USN", "s": "Yorktown remis en route ~19 nds, incendies maîtrisés — si bien réparé que la 2e frappe le croira intact (« 2e porte-avions »)", "u": 15}, {"t": 2310, "type": "attack", "side": "IJN", "s": "Attaque Tomonaga: 2 torpilles touchent le Yorktown (~14:43); gîte 23°; Tomonaga abattu", "u": 8}, {"t": 2325, "type": "sighting", "side": "USN", "s": "SBD de VS-5 (Adams, recherche lancée 13:30) localise le Hiryū: \"1 CV, 2 BB, 3 CA, 4 DD, 31°15'N 179°05'W\"", "u": 5}, {"t": 2335, "type": "course_change", "side": "USN", "s": "TF-16 vient au NO pour fermer la distance sur le Hiryū localisé par VS-5 (rapport Adams 14:45) avant de lancer", "u": 15}, {"t": 2340, "type": "other", "side": "USN", "s": "Buckmaster ordonne l'évacuation du Yorktown (crainte de chavirage)", "u": 10}, {"t": 2370, "type": "launch_start", "side": "USN", "s": "Enterprise lance 24 SBD (dont 10 ex-VB-3 du Yorktown) sur le Hiryū", "u": 10}, {"t": 2461, "type": "hit", "side": "USN", "s": "4 bombes sur le Hiryū (avant, ascenseur projeté contre l'îlot); incendies généralisés; attaque Hornet (17:30) et B-17 sans résultat ensuite", "u": 5}, {"t": 2520, "type": "course_change", "side": "IJN", "s": "Retraite générale de la force de Nagumo vers le NO au crépuscule (regroupement prévu avec le corps principal)", "u": 30}, {"t": 2580, "type": "other", "side": "USN", "s": "Recherche du soir de Norris (Vindicators VMSB-241) vers le CV en feu; aucun contact, météo se dégrade — le Vindicator de Norris est perdu (Norris et Pfc Whittington disparus)", "u": 15}, {"t": 2587, "type": "decision", "side": "USN", "s": "Spruance refuse la poursuite à l'ouest de nuit et fait route à l'est jusqu'à minuit — évite la tentative d'engagement nocturne de Yamamoto", "u": 15}, {"t": 2593, "type": "sinking", "side": "IJN", "s": "Le Sōryū coule (torpilles de l'Isokaze); Yanagimoto reste à bord (~711 morts)", "u": 5}, {"t": 2605, "type": "sinking", "side": "IJN", "s": "Le Kaga coule (torpilles du Hagikaze) (~811 morts — la plus lourde perte humaine des 4 CV)", "u": 5}, {"t": 2881, "type": "course_change", "side": "USN", "s": "Minuit: fin de la jambe est défensive; TF-16 vient au nord puis à l'ouest (plan annoncé de Spruance) pour être en position de frapper à l'aube", "u": 20}, {"t": 2895, "type": "decision", "side": "IJN", "s": "Yamamoto ordonne le regroupement pour un engagement de nuit / bombardement de Midway par CruDiv 7 — puis y renonce", "u": 30}, {"t": 3015, "type": "sighting", "side": "both", "s": "Le Tambor est aperçu par CruDiv 7; ordre de virage d'urgence simultané", "u": 10}, {"t": 3023, "type": "collision", "side": "IJN", "s": "Le Mogami éperonne le Mikuma: proue détruite, vitesse réduite à ~12 nds; les deux croiseurs + 2 DD restent en arrière", "u": 10}, {"t": 3055, "type": "decision", "side": "IJN", "s": "Yamamoto annule l'opération MI; retraite générale", "u": 15}, {"t": 3180, "type": "scuttling", "side": "IJN", "s": "L'Akagi est sabordé (torpilles de 4 destroyers), coule ~05:20", "u": 20}, {"t": 3190, "type": "scuttling", "side": "IJN", "s": "Le Makigumo torpille le Hiryū (Kaku et Yamaguchi restent à bord); il flotte encore des heures — photographié par un B4Y du Hōshō, des survivants seront repêchés", "u": 15}, {"t": 3210, "type": "course_change", "side": "USN", "s": "TF-16 reprend la poursuite vers l'ouest au matin (rapports de CV en flammes + contacts de la nuit)", "u": 30}, {"t": 3365, "type": "attack", "side": "USN", "s": "VMSB-241 attaque Mogami/Mikuma; le SBD de Fleming s'écrase sur la tourelle arrière du Mikuma", "u": 10}, {"t": 3432, "type": "sinking", "side": "IJN", "s": "Le Hiryū coule", "u": 10}, {"t": 3600, "type": "decision", "side": "USN", "s": "Décision de sauver le Yorktown: équipe de sauvetage à bord, remorquage par le Vireo, escorte constituée", "u": 60}, {"t": 3960, "type": "attack", "side": "USN", "s": "~58 SBD de TF-16 (puis B-17) attaquent le Tanikaze, seul — aucun coup; il abat 1 SBD", "u": 20}, {"t": 4725, "type": "sighting", "side": "USN", "s": "Reconnaissance matinale de l'Enterprise relocalise Mogami/Mikuma et leurs 2 DD; TF-16 met le cap dessus", "u": 15}, {"t": 4770, "type": "sighting", "side": "USN", "s": "2e contact du matin: \"2 CA, 2 DD, 28°55'N 175°10'E, cap 215, 15 nds\" (le même groupe Mogami/Mikuma, fixes d'estime divergents)", "u": 10}, {"t": 4800, "type": "launch_start", "side": "USN", "s": "TF-16 lance la 1re frappe sur Mogami/Mikuma (~26 SBD du Hornet)", "u": 15}, {"t": 4910, "type": "attack", "side": "USN", "s": "1re frappe: coups sur Mogami et Mikuma", "u": 15}, {"t": 4965, "type": "launch_start", "side": "USN", "s": "TF-16 lance la 2e frappe (31 SBD de l'Enterprise, mix VB-6/VS-6/VB-3)", "u": 15}, {"t": 5040, "type": "attack", "side": "USN", "s": "2e frappe: Mikuma dévasté; Mogami et un DD touchés", "u": 15}, {"t": 5130, "type": "launch_start", "side": "USN", "s": "TF-16 lance la 3e frappe (24 SBD du Hornet)", "u": 15}, {"t": 5136, "type": "hit", "side": "IJN", "s": "I-168 (Tanabe) torpille à travers l'écran: 2 torpilles dans le Yorktown, 1 dans le Hammann (coule en 4 min, explosion de ses grenades ASM)", "u": 5}, {"t": 5205, "type": "attack", "side": "USN", "s": "3e frappe: le Mikuma est achevé (coule dans la soirée); le Mogami s'échappe vers Truk", "u": 15}, {"t": 5467, "type": "course_change", "side": "USN", "s": "Spruance rompt la poursuite (carburant des destroyers, proximité de Wake) et fait route NE vers le ravitaillement", "u": 30}, {"t": 5490, "type": "sinking", "side": "IJN", "s": "Le Mikuma coule (première perte de croiseur lourd IJN)", "u": 60}, {"t": 6181, "type": "sinking", "side": "USN", "s": "Le Yorktown chavire et coule à l'aube", "u": 30}]